LICENSE
README.rst
setup.py
test_override/methods.py
test_override/my_class.py
test_override.egg-info/PKG-INFO
test_override.egg-info/SOURCES.txt
test_override.egg-info/dependency_links.txt
test_override.egg-info/top_level.txt