Metadata-Version: 2.1
Name: test-override
Version: 0.0.2
Summary: Test override
Home-page: UNKNOWN
Author: Linets Development Team
Author-email: cxasper23@gmail.com
License: MIT
Platform: UNKNOWN
Requires-Python: >=3.7
License-File: LICENSE
